a_selenium_get_source_from_all_frames/LICENSE
a_selenium_get_source_from_all_frames/README.MD
a_selenium_get_source_from_all_frames/__init__.py
a_selenium_get_source_from_all_frames/requirements.txt
a_selenium_get_source_from_all_frames/thirdparty.json
a_selenium_get_source_from_all_frames-0.10.dist-info/LICENSE.rst
a_selenium_get_source_from_all_frames-0.10.dist-info/METADATA
a_selenium_get_source_from_all_frames-0.10.dist-info/WHEEL
a_selenium_get_source_from_all_frames-0.10.dist-info/top_level.txt
a_selenium_get_source_from_all_frames-0.10.dist-info/RECORD
