Metadata-Version: 2.1
Name: a-selenium-get-source-from-all-frames
Version: 0.10
Summary: Get the whole updated HTML source code from every frame (not driver.page_source)
Home-page: https://github.com/hansalemaos/a_selenium_get_source_from_all_frames
Author: Johannes Fischer
Author-email: <aulasparticularesdealemaosp@gmail.com>
License: MIT
Keywords: Selenium,frames,source,html
Classifier: Development Status :: 4 - Beta
Classifier: Programming Language :: Python :: 3 :: Only
Classifier: Programming Language :: Python :: 3.9
Classifier: Topic :: Scientific/Engineering :: Visualization
Classifier: Topic :: Software Development :: Libraries :: Python Modules
Classifier: Topic :: Text Editors :: Text Processing
Classifier: Topic :: Text Processing :: General
Classifier: Topic :: Text Processing :: Indexing
Classifier: Topic :: Text Processing :: Filters
Classifier: Topic :: Utilities
License-File: LICENSE.rst
Requires-Dist: a-selenium2df
Requires-Dist: selenium
